MANIFEST.in
readme.md
scrapy_forum.db
setup.py
src/__init__.py
src/config.py
src/main.py
src/models.py
src/utils/__init__.py
src/utils/response.py
src/views/__init__.py
src/views/stats_acquisition.py
src/utils/__init__.py
src/utils/response.py
src/views/__init__.py
src/views/stats_acquisition.py
statsBotServer.egg-info/PKG-INFO
statsBotServer.egg-info/SOURCES.txt
statsBotServer.egg-info/dependency_links.txt
statsBotServer.egg-info/not-zip-safe
statsBotServer.egg-info/top_level.txt