Metadata-Version: 2.1
Name: statsBotServer
Version: 0.1
Summary: Server of the bot for collecting statistics
Home-page: https://github.com/MinaevaKsenia/statsBot
Author: Minaeva Ksenia
Author-email: minaeva.ksen@gmail.com
License: UNKNOWN
Platform: UNKNOWN
